Metadata-Version: 2.4
Name: claude-mira3
Version: 0.4.13
Summary: Persistent memory for Claude Code - semantic search, cross-session context, learned preferences
Project-URL: Homepage, https://github.com/Interstitch/MIRA3
Project-URL: Documentation, https://github.com/Interstitch/MIRA3#readme
Project-URL: Repository, https://github.com/Interstitch/MIRA3
Project-URL: Issues, https://github.com/Interstitch/MIRA3/issues
Author: Max
License-Expression: MIT
Keywords: claude,claude-code,conversation-history,mcp,memory,semantic-search
Classifier: Development Status :: 4 - Beta
Classifier: Intended Audience :: Developers
Classifier: License :: OSI Approved :: MIT License
Classifier: Programming Language :: Python :: 3
Classifier: Programming Language :: Python :: 3.10
Classifier: Programming Language :: Python :: 3.11
Classifier: Programming Language :: Python :: 3.12
Requires-Python: >=3.10
Requires-Dist: fastembed>=0.3.0
Requires-Dist: httpx>=0.25.0
Requires-Dist: mcp>=1.25.0
Requires-Dist: watchdog>=3.0.0
Provides-Extra: all
Requires-Dist: mypy>=1.0; extra == 'all'
Requires-Dist: psycopg2-binary>=2.9; extra == 'all'
Requires-Dist: pytest-asyncio>=0.21; extra == 'all'
Requires-Dist: pytest>=7.0; extra == 'all'
Requires-Dist: qdrant-client>=1.7.0; extra == 'all'
Requires-Dist: ruff>=0.1.0; extra == 'all'
Provides-Extra: dev
Requires-Dist: mypy>=1.0; extra == 'dev'
Requires-Dist: pytest-asyncio>=0.21; extra == 'dev'
Requires-Dist: pytest>=7.0; extra == 'dev'
Requires-Dist: ruff>=0.1.0; extra == 'dev'
Provides-Extra: remote
Requires-Dist: psycopg2-binary>=2.9; extra == 'remote'
Requires-Dist: qdrant-client>=1.7.0; extra == 'remote'
